verblaze/__init__.py
verblaze/api.py
verblaze/cli.py
verblaze/display_utils.py
verblaze/file_utils.py
verblaze/pattern_utils.py
verblaze/patterns.json
verblaze/string_extractor_utils.py
verblaze/string_utils.py
verblaze/translation_utils.py
verblaze-1.1.0.dist-info/METADATA
verblaze-1.1.0.dist-info/WHEEL
verblaze-1.1.0.dist-info/entry_points.txt
verblaze-1.1.0.dist-info/RECORD
