Metadata-Version: 2.4
Name: verblaze
Version: 1.1.0
Summary: Auto-Localization Generation Tool
Project-URL: Homepage, https://verblaze.com
Project-URL: Bug Tracker, https://github.com/Verblaze/verblaze_cli/issues
Author-email: 3K <info@verblaze.com>
Classifier: License :: OSI Approved :: MIT License
Classifier: Operating System :: OS Independent
Classifier: Programming Language :: Python :: 3
Requires-Python: >=3.6
Requires-Dist: click
Requires-Dist: requests
Requires-Dist: termcolor
Requires-Dist: unidecode
